MANIFEST.in
README.md
package.json
setup.py
restiro_spa_material/__init__.py
restiro_spa_material.egg-info/PKG-INFO
restiro_spa_material.egg-info/SOURCES.txt
restiro_spa_material.egg-info/dependency_links.txt
restiro_spa_material.egg-info/not-zip-safe
restiro_spa_material.egg-info/requires.txt
restiro_spa_material.egg-info/top_level.txt
restiro_spa_material/dist/docs.js
restiro_spa_material/dist/index.html
restiro_spa_material/dist/restiro.png
restiro_spa_material/dist/css/app.7873cbcd.css
restiro_spa_material/dist/css/chunk-vendors.e8208c80.css
restiro_spa_material/dist/fonts/MaterialIcons-Regular.012cf6a1.woff
restiro_spa_material/dist/fonts/MaterialIcons-Regular.570eb838.woff2
restiro_spa_material/dist/fonts/MaterialIcons-Regular.a37b0c01.ttf
restiro_spa_material/dist/fonts/MaterialIcons-Regular.e79bfd88.eot
restiro_spa_material/dist/js/app.1ba76023.js
restiro_spa_material/dist/js/app.1ba76023.js.map
restiro_spa_material/dist/js/chunk-vendors.3e1c6a36.js
restiro_spa_material/dist/js/chunk-vendors.3e1c6a36.js.map