Metadata-Version: 2.1
Name: restiro-spa-material
Version: 0.10.4
Summary: Restiro SPA Material template
Home-page: UNKNOWN
Author: Mahdi Ghane.g
License: UNKNOWN
Keywords: restiro,extension,http,rest,documentation
Platform: UNKNOWN
Classifier: Development Status :: 3 - Alpha
Classifier: Environment :: Console
Classifier: Environment :: Web Environment
Classifier: Intended Audience :: Developers
Classifier: License :: OSI Approved :: MIT License
Classifier: Operating System :: OS Independent
Classifier: Programming Language :: Python :: 3
Classifier: Topic :: Documentation
Classifier: Topic :: Utilities
